formatbibtex-0.0.2.dist-info/METADATA
formatbibtex-0.0.2.dist-info/WHEEL
formatbibtex-0.0.2.dist-info/entry_points.txt
formatbibtex-0.0.2.dist-info/licenses/LICENSE.txt
formatbibtex/__init__.py
formatbibtex-0.0.2.dist-info/RECORD
