Metadata-Version: 2.1
Name: formatbibtex
Version: 0.0.2
Summary: Bibtex formatter
Author-Email: Pierre Augier <pierre.augier@univ-grenoble-alpes.fr>
License: BSD-3-Clause
Requires-Python: >=3.9
Requires-Dist: bibtexparser>=2.0.0b3
